{
  "webmapId": "894f25fabd914310b4b529be3f81f2d4",
  "image": "https://publicweb-gis.s3.amazonaws.com/Images/MunicipalSeals/Franklin_CT.png",
  "title": "Town of Franklin, CT",
  "tabTitle": "Franklin GIS Parcel Viewer",
  "parcelLayerRestTitle": "CT Franklin Adv Viewer Parcels - Parcel Boundaries",
  "cssHeaderBackground": "#246d86",
  "cssViewBackground": "#9dbac7",
  "cssLayerFilterColor": "#9dbac7",
  "cssLayerFilterTextColor": "#474747",
  "customLegend": "no",
  "basemapTitle": "Franklin Basemap",
  "parcelRenderer": "#91C73D",
  "condos": "no",
  "imageUrl": "https://publicweb-gis.s3.amazonaws.com/Images/Bldg_Photos/Franklin_CT/",
  "showDisclaimer": "yes",
  "customDisclaimerPage": "no",
  "customDisclaimerMessage": "Please read and accept or else.",
  "welcomeImage": "https://publicweb-gis.s3.amazonaws.com/Images/MunicipalSeals/Franklin_CT.png",
  "customWelcomePage": "no",
  "customWelcomeMessage": "We want something different.",
  "DetailLinks": ["links", "ids", "vals", "sales"],
  "DetailLinksToInclude": ["links", "ids", "vals", "sales"],
  "accessorName": "- Kimberly Bechard, CCMA II – Assessor <br>",
  "includePermitLink": "no",
  "permitLink": "http://permitlinkusa-online.com/csp/franklinct/DocumentLink.PublicDLinkHome.cls",
  "propertyCardPdf": "no",
  "propertyCard": "https://www.propertyrecordcards.com/PropertyResults.aspx?towncode=053&uniqueid=",
  "pdf_Image": "https://publicweb-gis.s3.amazonaws.com/PDFs/CT_Franklin",
  "pdf_demographics": "https://publicweb-gis.s3.amazonaws.com/CT_Town_Profiles/Franklin_Demographics_2024.pdf",
  "useVisionForTaxBillUrl": "no",
  "tax_bill": "https://www.mytaxbill.org/inet/bill/parcel.do?town=franklin",
  "taxMapUrl": "https://publicweb-gis.s3.amazonaws.com/PDFs/CT_Franklin/Tax_Maps/TaxMap_",
  "useUniqueIdforParcelMap": "yes",
  "includeFilter": "yes",
  "parcelMapUrl": "CT_Franklin",
  "helpUrl": "https://publicweb-gis.s3.amazonaws.com/HelpMaterials/PublicViewer/HelpPublicViewer.html",
  "housingUrl": "https://publicweb-gis.s3.amazonaws.com/CT_Town_Profiles/Franklin_Housing_2024.pdf",
  "masterTable": "https://services1.arcgis.com/j6iFLXhyiD3XTMyD/ArcGIS/rest/services/CT_Franklin_Adv_Viewer_Parcels/FeatureServer/0",
  "condoLayer": "https://services1.arcgis.com/j6iFLXhyiD3XTMyD/ArcGIS/rest/services/CT_Franklin_Adv_Viewer_Parcels/FeatureServer/1",
  "noCondoLayer": "https://services1.arcgis.com/j6iFLXhyiD3XTMyD/ArcGIS/rest/services/CT_Franklin_Adv_Viewer_Parcels/FeatureServer/1",
  "parcelServiceTitle": "Parcel Boundaries",
  "parcelZoom": 2,
  "scale": 72000,
  "layers": [
    {
      "url": "https://services1.arcgis.com/j6iFLXhyiD3XTMyD/ArcGIS/rest/services/CT_Bethany_CAMA_Viewer/FeatureServer/8",
      "title": "Land Influence",
      "fieldName": "Influence_Type",
      "isVisible": false,
      "orderByField": "OBJECTID",
      "combobox1": "combo11",
      "combobox2": "combo12"
    }
  ]
}
